chatanalytics/__init__.py
chatanalytics/__main__.py
chatanalytics/chatter.py
chatter/__init__.py
chatter/__main__.py
chatter/chatter.py
chatter_bot/__init__.py
chatter_bot/__main__.py
chatanalytics-0.0.7.dist-info/LICENSE.md
chatanalytics-0.0.7.dist-info/METADATA
chatanalytics-0.0.7.dist-info/WHEEL
chatanalytics-0.0.7.dist-info/entry_points.txt
chatanalytics-0.0.7.dist-info/top_level.txt
chatanalytics-0.0.7.dist-info/RECORD
