Metadata-Version: 2.1
Name: chatanalytics
Version: 0.0.7
Summary: Twitch Chat Analytics Bot
Home-page: https://github.com/baxterda/chatanalytics
Author: Dawson Baxter
Author-email: dbaxtersoftware@gmail.com
License: MIT
Platform: UNKNOWN
Classifier: License :: OSI Approved :: MIT License
Classifier: Programming Language :: Python :: 3
Classifier: Programming Language :: Python :: 3.7
